ecoms/EasyCommunicationHandler.py
ecoms/__init__.py
ecoms/__main__.py
ecoms/master.py
ecoms/message_drop.py
ecoms/slave.py
EasyCommunications-0.1.5.dist-info/LICENSE
EasyCommunications-0.1.5.dist-info/METADATA
EasyCommunications-0.1.5.dist-info/WHEEL
EasyCommunications-0.1.5.dist-info/top_level.txt
EasyCommunications-0.1.5.dist-info/RECORD
