Metadata-Version: 2.1
Name: EasyCommunications
Version: 0.1.5
Summary: light-weight support for connecting different python scripts
Home-page: https://github.com/janluak/easycommunication
Author: Jan Lukas Braje
Author-email: ecoms@braje.org
License: Apache 2.0
Platform: UNKNOWN
Classifier: Development Status :: 3 - Alpha
Classifier: Intended Audience :: Information Technology
Classifier: License :: OSI Approved :: Apache Software License
Classifier: Operating System :: OS Independent
Classifier: Programming Language :: Python :: 3.6
Requires-Python: >=3.6
